{
  "ticker": "CEPF",
  "balanceSheet": {
    "symbol": "CEPF",
    "annualReports": [
      {
        "fiscalDateEnding": "2024-12-31",
        "reportedCurrency": "USD",
        "totalAssets": "306",
        "totalCurrentAssets": "0",
        "cashAndCashEquivalentsAtCarryingValue": "None",
        "cashAndShortTermInvestments": "None",
        "inventory": "None",
        "currentNetReceivables": "None",
        "totalNonCurrentAssets": "306",
        "propertyPlantEquipment": "None",
        "accumulatedDepreciationAmortizationPPE": "None",
        "intangibleAssets": "None",
        "intangibleAssetsExcludingGoodwill": "None",
        "goodwill": "None",
        "investments": "None",
        "longTermInvestments": "None",
        "shortTermInvestments": "None",
        "otherCurrentAssets": "None",
        "otherNonCurrentAssets": "None",
        "totalLiabilities": "2188",
        "totalCurrentLiabilities": "2188",
        "currentAccountsPayable": "None",
        "deferredRevenue": "None",
        "currentDebt": "None",
        "shortTermDebt": "None",
        "totalNonCurrentLiabilities": "0",
        "capitalLeaseObligations": "None",
        "longTermDebt": "None",
        "currentLongTermDebt": "None",
        "longTermDebtNoncurrent": "None",
        "shortLongTermDebtTotal": "None",
        "otherCurrentLiabilities": "None",
        "otherNonCurrentLiabilities": "None",
        "totalShareholderEquity": "-1882",
        "treasuryStock": "None",
        "retainedEarnings": "-26882",
        "commonStock": "None",
        "commonStockSharesOutstanding": "50900000"
      },
      {
        "fiscalDateEnding": "2023-12-31",
        "reportedCurrency": "USD",
        "totalAssets": "5164",
        "totalCurrentAssets": "5164",
        "cashAndCashEquivalentsAtCarryingValue": "None",
        "cashAndShortTermInvestments": "None",
        "inventory": "None",
        "currentNetReceivables": "None",
        "totalNonCurrentAssets": "0",
        "propertyPlantEquipment": "None",
        "accumulatedDepreciationAmortizationPPE": "None",
        "intangibleAssets": "None",
        "intangibleAssetsExcludingGoodwill": "None",
        "goodwill": "None",
        "investments": "None",
        "longTermInvestments": "None",
        "shortTermInvestments": "None",
        "otherCurrentAssets": "None",
        "otherNonCurrentAssets": "None",
        "totalLiabilities": "0",
        "totalCurrentLiabilities": "0",
        "currentAccountsPayable": "None",
        "deferredRevenue": "None",
        "currentDebt": "None",
        "shortTermDebt": "None",
        "totalNonCurrentLiabilities": "0",
        "capitalLeaseObligations": "None",
        "longTermDebt": "None",
        "currentLongTermDebt": "None",
        "longTermDebtNoncurrent": "None",
        "shortLongTermDebtTotal": "None",
        "otherCurrentLiabilities": "None",
        "otherNonCurrentLiabilities": "None",
        "totalShareholderEquity": "5164",
        "treasuryStock": "None",
        "retainedEarnings": "-19836",
        "commonStock": "None",
        "commonStockSharesOutstanding": "50900000"
      }
    ],
    "quarterlyReports": [
      {
        "fiscalDateEnding": "2025-09-30",
        "reportedCurrency": "USD",
        "totalAssets": "452581261",
        "totalCurrentAssets": "231829",
        "cashAndCashEquivalentsAtCarryingValue": "101829",
        "cashAndShortTermInvestments": "101829",
        "inventory": "None",
        "currentNetReceivables": "None",
        "totalNonCurrentAssets": "452349432",
        "propertyPlantEquipment": "None",
        "accumulatedDepreciationAmortizationPPE": "None",
        "intangibleAssets": "None",
        "intangibleAssetsExcludingGoodwill": "None",
        "goodwill": "None",
        "investments": "None",
        "longTermInvestments": "None",
        "shortTermInvestments": "None",
        "otherCurrentAssets": "130000",
        "otherNonCurrentAssets": "None",
        "totalLiabilities": "72329",
        "totalCurrentLiabilities": "72329",
        "currentAccountsPayable": "None",
        "deferredRevenue": "None",
        "currentDebt": "None",
        "shortTermDebt": "None",
        "totalNonCurrentLiabilities": "0",
        "capitalLeaseObligations": "None",
        "longTermDebt": "None",
        "currentLongTermDebt": "None",
        "longTermDebtNoncurrent": "None",
        "shortLongTermDebtTotal": "None",
        "otherCurrentLiabilities": "None",
        "otherNonCurrentLiabilities": "None",
        "totalShareholderEquity": "274823",
        "treasuryStock": "None",
        "retainedEarnings": "-153220",
        "commonStock": "452235324",
        "commonStockSharesOutstanding": "57150000"
      },
      {
        "fiscalDateEnding": "2025-06-30",
        "reportedCurrency": "USD",
        "totalAssets": "111265",
        "totalCurrentAssets": "None",
        "cashAndCashEquivalentsAtCarryingValue": "None",
        "cashAndShortTermInvestments": "None",
        "inventory": "None",
        "currentNetReceivables": "None",
        "totalNonCurrentAssets": "111265",
        "propertyPlantEquipment": "None",
        "accumulatedDepreciationAmortizationPPE": "None",
        "intangibleAssets": "None",
        "intangibleAssetsExcludingGoodwill": "None",
        "goodwill": "None",
        "investments": "None",
        "longTermInvestments": "None",
        "shortTermInvestments": "None",
        "otherCurrentAssets": "None",
        "otherNonCurrentAssets": "None",
        "totalLiabilities": "155650",
        "totalCurrentLiabilities": "155650",
        "currentAccountsPayable": "None",
        "deferredRevenue": "None",
        "currentDebt": "None",
        "shortTermDebt": "None",
        "totalNonCurrentLiabilities": "0",
        "capitalLeaseObligations": "None",
        "longTermDebt": "None",
        "currentLongTermDebt": "59507",
        "longTermDebtNoncurrent": "None",
        "shortLongTermDebtTotal": "None",
        "otherCurrentLiabilities": "None",
        "otherNonCurrentLiabilities": "None",
        "totalShareholderEquity": "-44385",
        "treasuryStock": "None",
        "retainedEarnings": "-69385",
        "commonStock": "None",
        "commonStockSharesOutstanding": "50900000"
      },
      {
        "fiscalDateEnding": "2025-03-31",
        "reportedCurrency": "USD",
        "totalAssets": "76031",
        "totalCurrentAssets": "None",
        "cashAndCashEquivalentsAtCarryingValue": "None",
        "cashAndShortTermInvestments": "None",
        "inventory": "None",
        "currentNetReceivables": "None",
        "totalNonCurrentAssets": "76031",
        "propertyPlantEquipment": "None",
        "accumulatedDepreciationAmortizationPPE": "None",
        "intangibleAssets": "None",
        "intangibleAssetsExcludingGoodwill": "None",
        "goodwill": "None",
        "investments": "None",
        "longTermInvestments": "None",
        "shortTermInvestments": "None",
        "otherCurrentAssets": "None",
        "otherNonCurrentAssets": "None",
        "totalLiabilities": "105061",
        "totalCurrentLiabilities": "105061",
        "currentAccountsPayable": "None",
        "deferredRevenue": "None",
        "currentDebt": "None",
        "shortTermDebt": "None",
        "totalNonCurrentLiabilities": "0",
        "capitalLeaseObligations": "None",
        "longTermDebt": "None",
        "currentLongTermDebt": "1882",
        "longTermDebtNoncurrent": "None",
        "shortLongTermDebtTotal": "None",
        "otherCurrentLiabilities": "None",
        "otherNonCurrentLiabilities": "None",
        "totalShareholderEquity": "-29030",
        "treasuryStock": "None",
        "retainedEarnings": "-54030",
        "commonStock": "None",
        "commonStockSharesOutstanding": "50900000"
      },
      {
        "fiscalDateEnding": "2024-12-31",
        "reportedCurrency": "USD",
        "totalAssets": "306",
        "totalCurrentAssets": "0",
        "cashAndCashEquivalentsAtCarryingValue": "None",
        "cashAndShortTermInvestments": "None",
        "inventory": "None",
        "currentNetReceivables": "None",
        "totalNonCurrentAssets": "306",
        "propertyPlantEquipment": "None",
        "accumulatedDepreciationAmortizationPPE": "None",
        "intangibleAssets": "None",
        "intangibleAssetsExcludingGoodwill": "None",
        "goodwill": "None",
        "investments": "None",
        "longTermInvestments": "None",
        "shortTermInvestments": "None",
        "otherCurrentAssets": "None",
        "otherNonCurrentAssets": "None",
        "totalLiabilities": "2188",
        "totalCurrentLiabilities": "2188",
        "currentAccountsPayable": "None",
        "deferredRevenue": "None",
        "currentDebt": "None",
        "shortTermDebt": "None",
        "totalNonCurrentLiabilities": "0",
        "capitalLeaseObligations": "None",
        "longTermDebt": "None",
        "currentLongTermDebt": "None",
        "longTermDebtNoncurrent": "None",
        "shortLongTermDebtTotal": "None",
        "otherCurrentLiabilities": "None",
        "otherNonCurrentLiabilities": "None",
        "totalShareholderEquity": "-1882",
        "treasuryStock": "None",
        "retainedEarnings": "-26882",
        "commonStock": "None",
        "commonStockSharesOutstanding": "50900000"
      },
      {
        "fiscalDateEnding": "2024-06-30",
        "reportedCurrency": "None",
        "totalAssets": "None",
        "totalCurrentAssets": "None",
        "cashAndCashEquivalentsAtCarryingValue": "None",
        "cashAndShortTermInvestments": "None",
        "inventory": "None",
        "currentNetReceivables": "None",
        "totalNonCurrentAssets": "None",
        "propertyPlantEquipment": "None",
        "accumulatedDepreciationAmortizationPPE": "None",
        "intangibleAssets": "None",
        "intangibleAssetsExcludingGoodwill": "None",
        "goodwill": "None",
        "investments": "None",
        "longTermInvestments": "None",
        "shortTermInvestments": "None",
        "otherCurrentAssets": "None",
        "otherNonCurrentAssets": "None",
        "totalLiabilities": "None",
        "totalCurrentLiabilities": "None",
        "currentAccountsPayable": "None",
        "deferredRevenue": "None",
        "currentDebt": "None",
        "shortTermDebt": "None",
        "totalNonCurrentLiabilities": "None",
        "capitalLeaseObligations": "None",
        "longTermDebt": "None",
        "currentLongTermDebt": "None",
        "longTermDebtNoncurrent": "None",
        "shortLongTermDebtTotal": "None",
        "otherCurrentLiabilities": "None",
        "otherNonCurrentLiabilities": "None",
        "totalShareholderEquity": "None",
        "treasuryStock": "None",
        "retainedEarnings": "None",
        "commonStock": "None",
        "commonStockSharesOutstanding": "50900000"
      }
    ]
  },
  "cashFlow": {
    "symbol": "CEPF",
    "annualReports": [
      {
        "fiscalDateEnding": "2024-12-31",
        "reportedCurrency": "USD",
        "operatingCashflow": "0",
        "paymentsForOperatingActivities": "None",
        "proceedsFromOperatingActivities": "None",
        "changeInOperatingLiabilities": "None",
        "changeInOperatingAssets": "None",
        "depreciationDepletionAndAmortization": "None",
        "capitalExpenditures": "0",
        "changeInReceivables": "None",
        "changeInInventory": "None",
        "profitLoss": "None",
        "cashflowFromInvestment": "None",
        "cashflowFromFinancing": "None",
        "proceedsFromRepaymentsOfShortTermDebt": "None",
        "paymentsForRepurchaseOfCommonStock": "None",
        "paymentsForRepurchaseOfEquity": "None",
        "paymentsForRepurchaseOfPreferredStock": "None",
        "dividendPayout": "None",
        "dividendPayoutCommonStock": "None",
        "dividendPayoutPreferredStock": "None",
        "proceedsFromIssuanceOfCommonStock": "None",
        "proceedsFromIssuanceOfLongTermDebtAndCapitalSecuritiesNet": "None",
        "proceedsFromIssuanceOfPreferredStock": "None",
        "proceedsFromRepurchaseOfEquity": "None",
        "proceedsFromSaleOfTreasuryStock": "None",
        "changeInCashAndCashEquivalents": "None",
        "changeInExchangeRate": "None",
        "netIncome": "-7046"
      },
      {
        "fiscalDateEnding": "2023-12-31",
        "reportedCurrency": "USD",
        "operatingCashflow": "0",
        "paymentsForOperatingActivities": "None",
        "proceedsFromOperatingActivities": "None",
        "changeInOperatingLiabilities": "None",
        "changeInOperatingAssets": "None",
        "depreciationDepletionAndAmortization": "None",
        "capitalExpenditures": "0",
        "changeInReceivables": "None",
        "changeInInventory": "None",
        "profitLoss": "None",
        "cashflowFromInvestment": "None",
        "cashflowFromFinancing": "None",
        "proceedsFromRepaymentsOfShortTermDebt": "None",
        "paymentsForRepurchaseOfCommonStock": "None",
        "paymentsForRepurchaseOfEquity": "None",
        "paymentsForRepurchaseOfPreferredStock": "None",
        "dividendPayout": "None",
        "dividendPayoutCommonStock": "None",
        "dividendPayoutPreferredStock": "None",
        "proceedsFromIssuanceOfCommonStock": "None",
        "proceedsFromIssuanceOfLongTermDebtAndCapitalSecuritiesNet": "None",
        "proceedsFromIssuanceOfPreferredStock": "None",
        "proceedsFromRepurchaseOfEquity": "None",
        "proceedsFromSaleOfTreasuryStock": "None",
        "changeInCashAndCashEquivalents": "None",
        "changeInExchangeRate": "None",
        "netIncome": "-3472"
      }
    ],
    "quarterlyReports": [
      {
        "fiscalDateEnding": "2025-09-30",
        "reportedCurrency": "USD",
        "operatingCashflow": "-3375",
        "paymentsForOperatingActivities": "None",
        "proceedsFromOperatingActivities": "None",
        "changeInOperatingLiabilities": "None",
        "changeInOperatingAssets": "None",
        "depreciationDepletionAndAmortization": "None",
        "capitalExpenditures": "0",
        "changeInReceivables": "None",
        "changeInInventory": "None",
        "profitLoss": "None",
        "cashflowFromInvestment": "None",
        "cashflowFromFinancing": "450105116",
        "proceedsFromRepaymentsOfShortTermDebt": "None",
        "paymentsForRepurchaseOfCommonStock": "None",
        "paymentsForRepurchaseOfEquity": "None",
        "paymentsForRepurchaseOfPreferredStock": "None",
        "dividendPayout": "None",
        "dividendPayoutCommonStock": "None",
        "dividendPayoutPreferredStock": "None",
        "proceedsFromIssuanceOfCommonStock": "None",
        "proceedsFromIssuanceOfLongTermDebtAndCapitalSecuritiesNet": "None",
        "proceedsFromIssuanceOfPreferredStock": "None",
        "proceedsFromRepurchaseOfEquity": "None",
        "proceedsFromSaleOfTreasuryStock": "None",
        "changeInCashAndCashEquivalents": "None",
        "changeInExchangeRate": "None",
        "netIncome": "1688318"
      },
      {
        "fiscalDateEnding": "2025-06-30",
        "reportedCurrency": "USD",
        "operatingCashflow": "-57625",
        "paymentsForOperatingActivities": "None",
        "proceedsFromOperatingActivities": "None",
        "changeInOperatingLiabilities": "None",
        "changeInOperatingAssets": "None",
        "depreciationDepletionAndAmortization": "None",
        "capitalExpenditures": "0",
        "changeInReceivables": "None",
        "changeInInventory": "None",
        "profitLoss": "None",
        "cashflowFromInvestment": "None",
        "cashflowFromFinancing": "57625",
        "proceedsFromRepaymentsOfShortTermDebt": "None",
        "paymentsForRepurchaseOfCommonStock": "None",
        "paymentsForRepurchaseOfEquity": "None",
        "paymentsForRepurchaseOfPreferredStock": "None",
        "dividendPayout": "None",
        "dividendPayoutCommonStock": "None",
        "dividendPayoutPreferredStock": "None",
        "proceedsFromIssuanceOfCommonStock": "None",
        "proceedsFromIssuanceOfLongTermDebtAndCapitalSecuritiesNet": "None",
        "proceedsFromIssuanceOfPreferredStock": "None",
        "proceedsFromRepurchaseOfEquity": "None",
        "proceedsFromSaleOfTreasuryStock": "None",
        "changeInCashAndCashEquivalents": "None",
        "changeInExchangeRate": "None",
        "netIncome": "-15355"
      },
      {
        "fiscalDateEnding": "2025-03-31",
        "reportedCurrency": "USD",
        "operatingCashflow": "-1882",
        "paymentsForOperatingActivities": "None",
        "proceedsFromOperatingActivities": "None",
        "changeInOperatingLiabilities": "None",
        "changeInOperatingAssets": "None",
        "depreciationDepletionAndAmortization": "None",
        "capitalExpenditures": "0",
        "changeInReceivables": "None",
        "changeInInventory": "None",
        "profitLoss": "None",
        "cashflowFromInvestment": "None",
        "cashflowFromFinancing": "1882",
        "proceedsFromRepaymentsOfShortTermDebt": "None",
        "paymentsForRepurchaseOfCommonStock": "None",
        "paymentsForRepurchaseOfEquity": "None",
        "paymentsForRepurchaseOfPreferredStock": "None",
        "dividendPayout": "None",
        "dividendPayoutCommonStock": "None",
        "dividendPayoutPreferredStock": "None",
        "proceedsFromIssuanceOfCommonStock": "None",
        "proceedsFromIssuanceOfLongTermDebtAndCapitalSecuritiesNet": "None",
        "proceedsFromIssuanceOfPreferredStock": "None",
        "proceedsFromRepurchaseOfEquity": "None",
        "proceedsFromSaleOfTreasuryStock": "None",
        "changeInCashAndCashEquivalents": "None",
        "changeInExchangeRate": "None",
        "netIncome": "-27148"
      },
      {
        "fiscalDateEnding": "2024-12-31",
        "reportedCurrency": "USD",
        "operatingCashflow": "0",
        "paymentsForOperatingActivities": "None",
        "proceedsFromOperatingActivities": "None",
        "changeInOperatingLiabilities": "None",
        "changeInOperatingAssets": "None",
        "depreciationDepletionAndAmortization": "None",
        "capitalExpenditures": "0",
        "changeInReceivables": "None",
        "changeInInventory": "None",
        "profitLoss": "None",
        "cashflowFromInvestment": "None",
        "cashflowFromFinancing": "None",
        "proceedsFromRepaymentsOfShortTermDebt": "None",
        "paymentsForRepurchaseOfCommonStock": "None",
        "paymentsForRepurchaseOfEquity": "None",
        "paymentsForRepurchaseOfPreferredStock": "None",
        "dividendPayout": "None",
        "dividendPayoutCommonStock": "None",
        "dividendPayoutPreferredStock": "None",
        "proceedsFromIssuanceOfCommonStock": "None",
        "proceedsFromIssuanceOfLongTermDebtAndCapitalSecuritiesNet": "None",
        "proceedsFromIssuanceOfPreferredStock": "None",
        "proceedsFromRepurchaseOfEquity": "None",
        "proceedsFromSaleOfTreasuryStock": "None",
        "changeInCashAndCashEquivalents": "None",
        "changeInExchangeRate": "None",
        "netIncome": "-4166"
      },
      {
        "fiscalDateEnding": "2024-06-30",
        "reportedCurrency": "USD",
        "operatingCashflow": "0",
        "paymentsForOperatingActivities": "None",
        "proceedsFromOperatingActivities": "None",
        "changeInOperatingLiabilities": "None",
        "changeInOperatingAssets": "None",
        "depreciationDepletionAndAmortization": "None",
        "capitalExpenditures": "0",
        "changeInReceivables": "None",
        "changeInInventory": "None",
        "profitLoss": "None",
        "cashflowFromInvestment": "None",
        "cashflowFromFinancing": "0",
        "proceedsFromRepaymentsOfShortTermDebt": "None",
        "paymentsForRepurchaseOfCommonStock": "None",
        "paymentsForRepurchaseOfEquity": "None",
        "paymentsForRepurchaseOfPreferredStock": "None",
        "dividendPayout": "None",
        "dividendPayoutCommonStock": "None",
        "dividendPayoutPreferredStock": "None",
        "proceedsFromIssuanceOfCommonStock": "None",
        "proceedsFromIssuanceOfLongTermDebtAndCapitalSecuritiesNet": "None",
        "proceedsFromIssuanceOfPreferredStock": "None",
        "proceedsFromRepurchaseOfEquity": "None",
        "proceedsFromSaleOfTreasuryStock": "None",
        "changeInCashAndCashEquivalents": "None",
        "changeInExchangeRate": "None",
        "netIncome": "-2880"
      }
    ]
  },
  "incomeStatement": {
    "symbol": "CEPF",
    "annualReports": [
      {
        "fiscalDateEnding": "2024-12-31",
        "reportedCurrency": "USD",
        "grossProfit": "None",
        "totalRevenue": "0",
        "costOfRevenue": "None",
        "costofGoodsAndServicesSold": "None",
        "operatingIncome": "-7046",
        "sellingGeneralAndAdministrative": "7046",
        "researchAndDevelopment": "None",
        "operatingExpenses": "7046",
        "investmentIncomeNet": "None",
        "netInterestIncome": "None",
        "interestIncome": "None",
        "interestExpense": "None",
        "nonInterestIncome": "None",
        "otherNonOperatingIncome": "None",
        "depreciation": "None",
        "depreciationAndAmortization": "None",
        "incomeBeforeTax": "-7046",
        "incomeTaxExpense": "None",
        "interestAndDebtExpense": "None",
        "netIncomeFromContinuingOperations": "-7046",
        "comprehensiveIncomeNetOfTax": "None",
        "ebit": "None",
        "ebitda": "-7046",
        "netIncome": "-7046"
      },
      {
        "fiscalDateEnding": "2023-12-31",
        "reportedCurrency": "USD",
        "grossProfit": "None",
        "totalRevenue": "0",
        "costOfRevenue": "None",
        "costofGoodsAndServicesSold": "None",
        "operatingIncome": "-3472",
        "sellingGeneralAndAdministrative": "3472",
        "researchAndDevelopment": "None",
        "operatingExpenses": "3472",
        "investmentIncomeNet": "None",
        "netInterestIncome": "None",
        "interestIncome": "None",
        "interestExpense": "None",
        "nonInterestIncome": "None",
        "otherNonOperatingIncome": "None",
        "depreciation": "None",
        "depreciationAndAmortization": "None",
        "incomeBeforeTax": "-3472",
        "incomeTaxExpense": "None",
        "interestAndDebtExpense": "None",
        "netIncomeFromContinuingOperations": "-3472",
        "comprehensiveIncomeNetOfTax": "None",
        "ebit": "None",
        "ebitda": "-3472",
        "netIncome": "-3472"
      }
    ],
    "quarterlyReports": [
      {
        "fiscalDateEnding": "2025-09-30",
        "reportedCurrency": "USD",
        "grossProfit": "None",
        "totalRevenue": "0",
        "costOfRevenue": "None",
        "costofGoodsAndServicesSold": "None",
        "operatingIncome": "-118964",
        "sellingGeneralAndAdministrative": "105416",
        "researchAndDevelopment": "None",
        "operatingExpenses": "105416",
        "investmentIncomeNet": "None",
        "netInterestIncome": "1807282",
        "interestIncome": "1807282",
        "interestExpense": "None",
        "nonInterestIncome": "None",
        "otherNonOperatingIncome": "None",
        "depreciation": "None",
        "depreciationAndAmortization": "None",
        "incomeBeforeTax": "1688318",
        "incomeTaxExpense": "None",
        "interestAndDebtExpense": "None",
        "netIncomeFromContinuingOperations": "1688318",
        "comprehensiveIncomeNetOfTax": "None",
        "ebit": "None",
        "ebitda": "-118964",
        "netIncome": "1688318"
      },
      {
        "fiscalDateEnding": "2025-06-30",
        "reportedCurrency": "USD",
        "grossProfit": "None",
        "totalRevenue": "0",
        "costOfRevenue": "None",
        "costofGoodsAndServicesSold": "None",
        "operatingIncome": "-15355",
        "sellingGeneralAndAdministrative": "15355",
        "researchAndDevelopment": "None",
        "operatingExpenses": "15355",
        "investmentIncomeNet": "None",
        "netInterestIncome": "None",
        "interestIncome": "None",
        "interestExpense": "None",
        "nonInterestIncome": "None",
        "otherNonOperatingIncome": "None",
        "depreciation": "None",
        "depreciationAndAmortization": "None",
        "incomeBeforeTax": "-15355",
        "incomeTaxExpense": "None",
        "interestAndDebtExpense": "None",
        "netIncomeFromContinuingOperations": "-15355",
        "comprehensiveIncomeNetOfTax": "None",
        "ebit": "None",
        "ebitda": "-15355",
        "netIncome": "-15355"
      },
      {
        "fiscalDateEnding": "2025-03-31",
        "reportedCurrency": "USD",
        "grossProfit": "None",
        "totalRevenue": "0",
        "costOfRevenue": "None",
        "costofGoodsAndServicesSold": "None",
        "operatingIncome": "-27148",
        "sellingGeneralAndAdministrative": "27148",
        "researchAndDevelopment": "None",
        "operatingExpenses": "27148",
        "investmentIncomeNet": "None",
        "netInterestIncome": "None",
        "interestIncome": "None",
        "interestExpense": "None",
        "nonInterestIncome": "None",
        "otherNonOperatingIncome": "None",
        "depreciation": "None",
        "depreciationAndAmortization": "None",
        "incomeBeforeTax": "-27148",
        "incomeTaxExpense": "None",
        "interestAndDebtExpense": "None",
        "netIncomeFromContinuingOperations": "-27148",
        "comprehensiveIncomeNetOfTax": "None",
        "ebit": "None",
        "ebitda": "-27148",
        "netIncome": "-27148"
      },
      {
        "fiscalDateEnding": "2024-12-31",
        "reportedCurrency": "USD",
        "grossProfit": "None",
        "totalRevenue": "0",
        "costOfRevenue": "None",
        "costofGoodsAndServicesSold": "None",
        "operatingIncome": "-4166",
        "sellingGeneralAndAdministrative": "4166",
        "researchAndDevelopment": "None",
        "operatingExpenses": "4166",
        "investmentIncomeNet": "None",
        "netInterestIncome": "None",
        "interestIncome": "None",
        "interestExpense": "None",
        "nonInterestIncome": "None",
        "otherNonOperatingIncome": "None",
        "depreciation": "None",
        "depreciationAndAmortization": "None",
        "incomeBeforeTax": "-4166",
        "incomeTaxExpense": "None",
        "interestAndDebtExpense": "None",
        "netIncomeFromContinuingOperations": "-4166",
        "comprehensiveIncomeNetOfTax": "None",
        "ebit": "None",
        "ebitda": "None",
        "netIncome": "-4166"
      },
      {
        "fiscalDateEnding": "2024-06-30",
        "reportedCurrency": "USD",
        "grossProfit": "None",
        "totalRevenue": "0",
        "costOfRevenue": "None",
        "costofGoodsAndServicesSold": "None",
        "operatingIncome": "-2880",
        "sellingGeneralAndAdministrative": "2880",
        "researchAndDevelopment": "None",
        "operatingExpenses": "2880",
        "investmentIncomeNet": "None",
        "netInterestIncome": "None",
        "interestIncome": "None",
        "interestExpense": "None",
        "nonInterestIncome": "None",
        "otherNonOperatingIncome": "None",
        "depreciation": "None",
        "depreciationAndAmortization": "None",
        "incomeBeforeTax": "-2880",
        "incomeTaxExpense": "None",
        "interestAndDebtExpense": "None",
        "netIncomeFromContinuingOperations": "-2880",
        "comprehensiveIncomeNetOfTax": "None",
        "ebit": "None",
        "ebitda": "-2880",
        "netIncome": "-2880"
      }
    ]
  }
}